RUP-0.1.17.dist-info/DESCRIPTION.rst
RUP-0.1.17.dist-info/METADATA
RUP-0.1.17.dist-info/RECORD
RUP-0.1.17.dist-info/WHEEL
RUP-0.1.17.dist-info/entry_points.txt
RUP-0.1.17.dist-info/metadata.json
RUP-0.1.17.dist-info/top_level.txt
rup/__init__.py
rup/__main__.py
rup/__main_light__.py
rup/collector.py
rup/http_api_auth.py
rup/light.py
rup/processor.py
rup/rules.py
rup/util.py
rup/watcher.py
test/__init__.py
test/test_determine_best_run.py
test/test_determine_run_number.py
test/test_rule_matching.py
test/test_rule_parser.py
test/test_rule_templates.py
