Metadata-Version: 2.0
Name: RUP
Version: 0.1.17
Summary: UNKNOWN
Home-page: https://git.kern.phys.au.dk/ausa/RUP
Author: Michael Munch
Author-email: mm@phys.au.dk
License: MIT
Platform: UNKNOWN
Requires-Dist: RunDB-client (>=0.4)
Requires-Dist: docker
Requires-Dist: futures
Requires-Dist: pyaml
Requires-Dist: python-dateutil
Requires-Dist: requests (>2)
Requires-Dist: watchdog
